rqrcode-0.0.1.dist-info/METADATA
rqrcode-0.0.1.dist-info/WHEEL
rqrcode-0.0.1.dist-info/license_files/LICENSE
rqrcode/__init__.py
rqrcode/rqrcode.abi3.so
rqrcode-0.0.1.dist-info/RECORD
