Metadata-Version: 2.1
Name: rqrcode
Version: 0.0.1
Classifier: Programming Language :: Rust
Classifier: Programming Language :: Python :: Implementation :: CPython
Classifier: Programming Language :: Python :: Implementation :: PyPy
License-File: LICENSE
Summary: Python qrcode extension developed with rust.
Home-Page: https://github.com/korykim
Author: korykim@vip.qq.com
Author-email: korykim@vip.qq.com
License: MIT
Requires-Python: >=3.7
Project-URL: documentation, https://github.com/korykim/rqrcode
Project-URL: repository, https://github.com/korykim/rqrcode
